{"chunk_definitions":[{"chunk_id":"csetup_chunk","chunk_label":"setup","document_id":"18C6B64B","expansion_state":0,"options":{"engine":"r","include":false,"label":"setup"},"row":9,"row_count":1,"visible":true},{"chunk_id":"csflf32qm9rtd","chunk_label":"unnamed-chunk-2","document_id":"18C6B64B","expansion_state":0,"options":{"engine":"r","label":"unnamed-chunk-192"},"row":35,"row_count":1,"visible":true},{"chunk_id":"cize2kyp5t7sm","chunk_label":"unnamed-chunk-3","document_id":"18C6B64B","expansion_state":0,"options":{"engine":"r","label":"unnamed-chunk-200"},"row":52,"row_count":1,"visible":true},{"chunk_id":"c7zkjum10d7tw","chunk_label":"unnamed-chunk-4","document_id":"18C6B64B","expansion_state":0,"options":{"engine":"r","label":"unnamed-chunk-206"},"row":66,"row_count":1,"visible":true},{"chunk_id":"cnjmp3qc33xx4","chunk_label":"unnamed-chunk-5","document_id":"18C6B64B","expansion_state":0,"options":{"engine":"r","label":"unnamed-chunk-213"},"row":77,"row_count":1,"visible":true},{"chunk_id":"ctqyfndopcuu8","chunk_label":"unnamed-chunk-6","document_id":"18C6B64B","expansion_state":0,"options":{"engine":"r","label":"unnamed-chunk-209"},"row":88,"row_count":1,"visible":true},{"chunk_id":"cz13ozu7f8i19","chunk_label":"unnamed-chunk-7","document_id":"18C6B64B","expansion_state":0,"options":{"engine":"r","label":"unnamed-chunk-214"},"row":103,"row_count":1,"visible":true},{"chunk_id":"cwguhq2rvsnb6","chunk_label":"unnamed-chunk-8","document_id":"18C6B64B","expansion_state":0,"options":{"engine":"r","label":"unnamed-chunk-175"},"row":112,"row_count":1,"visible":true}],"doc_write_time":1563566254}